review_gate_mcp/__init__.py
review_gate_mcp/server.py
review_gate_mcp-2.0.2.dist-info/METADATA
review_gate_mcp-2.0.2.dist-info/WHEEL
review_gate_mcp-2.0.2.dist-info/entry_points.txt
review_gate_mcp-2.0.2.dist-info/licenses/LICENSE
review_gate_mcp-2.0.2.dist-info/RECORD
