Metadata-Version: 2.4
Name: review-gate-mcp
Version: 2.0.2
Summary: Modern MCP server for Review Gate - AI-powered code review and interaction tool
Project-URL: Homepage, https://github.com/abhishekbhakat/Review-Gate
Project-URL: Repository, https://github.com/abhishekbhakat/Review-Gate
Project-URL: Issues, https://github.com/abhishekbhakat/Review-Gate/issues
Project-URL: Documentation, https://github.com/abhishekbhakat/Review-Gate/blob/main/README.md
Author-email: Lakshman Turlapati <lakshman@example.com>, Abhishek Bhakat <abhishek.bhakat@hotmail.com>
License: MIT
License-File: LICENSE
Keywords: ai,code-review,llm,mcp
Classifier: Development Status :: 4 - Beta
Classifier: Intended Audience :: Developers
Classifier: License :: OSI Approved :: MIT License
Classifier: Programming Language :: Python :: 3
Classifier: Programming Language :: Python :: 3.10
Classifier: Programming Language :: Python :: 3.11
Classifier: Programming Language :: Python :: 3.12
Classifier: Topic :: Scientific/Engineering :: Artificial Intelligence
Classifier: Topic :: Software Development :: Libraries :: Python Modules
Requires-Python: >=3.10
Requires-Dist: mcp>=1.9.2
Provides-Extra: all
Requires-Dist: faster-whisper>=1.0.0; extra == 'all'
Requires-Dist: pillow>=10.0.0; extra == 'all'
Provides-Extra: dev
Requires-Dist: mypy>=1.0.0; extra == 'dev'
Requires-Dist: pre-commit>=3.0.0; extra == 'dev'
Requires-Dist: pytest-asyncio>=0.21.0; extra == 'dev'
Requires-Dist: pytest>=7.0.0; extra == 'dev'
Requires-Dist: ruff>=0.1.0; extra == 'dev'
Provides-Extra: image
Requires-Dist: pillow>=10.0.0; extra == 'image'
Provides-Extra: speech
Requires-Dist: faster-whisper>=1.0.0; extra == 'speech'
